yacp/__init__.py
yacp/section.py
yet_another_config_parser-0.3.0.dist-info/LICENSE
yet_another_config_parser-0.3.0.dist-info/METADATA
yet_another_config_parser-0.3.0.dist-info/WHEEL
yet_another_config_parser-0.3.0.dist-info/RECORD
