Metadata-Version: 2.1
Name: yet-another-config-parser
Version: 0.3.0
Summary: Unified argument and configuration parser
Home-page: https://gitlab.com/aragaer/yacp/
License: MIT
Author: aragaer
Author-email: aragaer@gmail.com
Requires-Python: >=3.10,<4.0
Classifier: License :: OSI Approved :: MIT License
Classifier: Programming Language :: Python :: 3
Classifier: Programming Language :: Python :: 3.10
Classifier: Programming Language :: Python :: 3.11
Classifier: Programming Language :: Python :: 3.12
Project-URL: Repository, https://gitlab.com/aragaer/yacp/
